ntimage/__init__.py
ntimage/core/__init__.py
ntimage/core/create.py
ntimage/core/io.py
ntimage/core/ntimage.py
ntimage/ops/__init__.py
ntimage/ops/image.py
ntimage/ops/intensity.py
ntimage/ops/logic.py
ntimage/ops/math.py
ntimage/ops/shape.py
ntimage/plotting/__init__.py
ntimage/plotting/grid.py
ntimage/plotting/hist.py
ntimage/plotting/ortho.py
ntimage/plotting/plot.py
ntimage/utils/__init__.py
ntimage/utils/datatypes.py
ntimage/utils/methods.py
nitrain_image-0.1.1.dist-info/LICENSE
nitrain_image-0.1.1.dist-info/METADATA
nitrain_image-0.1.1.dist-info/WHEEL
nitrain_image-0.1.1.dist-info/RECORD
